ipyforcegraph/__init__.py
ipyforcegraph/_base.py
ipyforcegraph/constants.py
ipyforcegraph/graphs.py
ipyforcegraph/js.py
ipyforcegraph/py.typed
ipyforcegraph/serializers.py
ipyforcegraph/trait_utils.py
ipyforcegraph/behaviors/__init__.py
ipyforcegraph/behaviors/_base.py
ipyforcegraph/behaviors/forces.py
ipyforcegraph/behaviors/particles.py
ipyforcegraph/behaviors/recording.py
ipyforcegraph/behaviors/scales.py
ipyforcegraph/behaviors/selection.py
ipyforcegraph/behaviors/shapes.py
ipyforcegraph/behaviors/tooltip.py
ipyforcegraph/behaviors/wrappers.py
ipyforcegraph/sources/__init__.py
ipyforcegraph/sources/dataframe.py
ipyforcegraph/sources/dodo.py
ipyforcegraph/sources/widget.py
ipyforcegraph/tests/__init__.py
ipyforcegraph/tests/conftest.py
ipyforcegraph/tests/test_dag_widget.py
ipyforcegraph/tests/test_dodo_source.py
ipyforcegraph/tests/test_meta.py
ipyforcegraph/tests/test_scales.py
ipyforcegraph/tests/test_serializers.py
ipyforcegraph/tests/test_validators.py
ipyforcegraph/tests/test_widget_model_meta.py
ipyforcegraph/tests/test_widget_source.py
ipyforcegraph/tests/test_wrappers.py
ipyforcegraph-0.4.1.data/data/share/jupyter/labextensions/@jupyrdf/jupyter-forcegraph/package.json
ipyforcegraph-0.4.1.data/data/share/jupyter/labextensions/@jupyrdf/jupyter-forcegraph/static/106.faa6f83972ebb93ea364.js
ipyforcegraph-0.4.1.data/data/share/jupyter/labextensions/@jupyrdf/jupyter-forcegraph/static/106.faa6f83972ebb93ea364.js.map
ipyforcegraph-0.4.1.data/data/share/jupyter/labextensions/@jupyrdf/jupyter-forcegraph/static/125.cbe545e870b647d5ab9b.js
ipyforcegraph-0.4.1.data/data/share/jupyter/labextensions/@jupyrdf/jupyter-forcegraph/static/125.cbe545e870b647d5ab9b.js.map
ipyforcegraph-0.4.1.data/data/share/jupyter/labextensions/@jupyrdf/jupyter-forcegraph/static/132.3c74277b7584606eb909.js
ipyforcegraph-0.4.1.data/data/share/jupyter/labextensions/@jupyrdf/jupyter-forcegraph/static/132.3c74277b7584606eb909.js.map
ipyforcegraph-0.4.1.dist-info/LICENSE.txt
ipyforcegraph-0.4.1.dist-info/WHEEL
ipyforcegraph-0.4.1.dist-info/METADATA
ipyforcegraph-0.4.1.dist-info/RECORD
