Metadata-Version: 2.1
Name: ipyforcegraph
Version: 0.4.1
Summary: 2D and 3D force-directed graph widgets for Jupyter
Author-email: ipyforcegraph contributors <jupyrdf@users.noreply.github.com>
Requires-Python: >=3.8
Classifier: Framework :: Jupyter
Classifier: Framework :: Jupyter :: JupyterLab
Classifier: Framework :: Jupyter :: JupyterLab :: 3
Classifier: Framework :: Jupyter :: JupyterLab :: Extensions
Classifier: Framework :: Jupyter :: JupyterLab :: Extensions :: Prebuilt
Classifier: Intended Audience :: Developers
Classifier: Intended Audience :: Science/Research
Classifier: License :: OSI Approved :: BSD License
Classifier: Programming Language :: Python :: 3 :: Only
Classifier: Programming Language :: Python :: 3.8
Classifier: Programming Language :: Python :: 3.9
Classifier: Programming Language :: Python :: 3.10
Classifier: Programming Language :: Python :: 3.11
Requires-Dist: ipywidgets<9,>=8.0.4
Requires-Dist: numcodecs
Requires-Dist: pandas
Requires-Dist: traittypes
Project-URL: Bug Tracker, https://github.com/jupyrdf/ipyforcegraph/issues
Project-URL: Changelog, https://github.com/jupyrdf/ipyforcegraph/blob/main/CHANGELOG.md
Project-URL: Conda Forge, https://github.com/conda-forge/ipyforcegraph-feedstock
Project-URL: Documentation, https://ipyforcegraph.rtfd.io
Project-URL: NPM, https://www.npmjs.com/package/@jupyrdf/jupyter-forcegraph
Project-URL: PyPI, https://pypi.org/project/ipyforcegraph
Project-URL: Source, https://github.com/jupyrdf/ipyforcegraph
